setup.py
aluminium/__init__.py
aluminium/help.py
aluminium.egg-info/PKG-INFO
aluminium.egg-info/SOURCES.txt
aluminium.egg-info/dependency_links.txt
aluminium.egg-info/entry_points.txt
aluminium.egg-info/top_level.txt
aluminium/errors/__init__.py
aluminium/modules/__init__.py
aluminium/utils/__init__.py