Metadata-Version: 1.1
Name: aluminium
Version: 0.0.1
Summary: System administration toolkit.
Home-page: https://github.com/thee-engineer/aluminium
Author: Alexandru-Paul Copil (thee-engineer)
Author-email: alexandru.p.copil@gmail.com
License: GNU General Public License v3 (GPLv3)
Keywords: kit system administrator sys-admin sysadmin admin unix tools
Platform: UNKNOWN
Classifier: Development Status :: 1 - Planning
Classifier: Intended Audience :: Developers
Classifier: Intended Audience :: System Administrators
Classifier: Intended Audience :: Information Technology
Classifier: Topic :: System
Classifier: Topic :: Utilities
Classifier: Environment :: Other Environment
Classifier: License :: OSI Approved :: GNU General Public License v3 (GPLv3)
Classifier: Natural Language :: English
Classifier: Programming Language :: Python :: 2.7
Classifier: Programming Language :: Python :: 3.6
Classifier: Operating System :: Unix
